PyCyphORM/__init__.py
PyCyphORM/cli.py
PyCyphORM/lib/__init__.py
PyCyphORM/lib/adapter.py
PyCyphORM/lib/orm.py
PyCyphORM-0.1.3.dist-info/METADATA
PyCyphORM-0.1.3.dist-info/WHEEL
PyCyphORM-0.1.3.dist-info/entry_points.txt
PyCyphORM-0.1.3.dist-info/top_level.txt
PyCyphORM-0.1.3.dist-info/RECORD
