Metadata-Version: 2.1
Name: PyCyphORM
Version: 0.1.3
Summary: A Minimalistic SQLite InMemory Encrypted ORM
Author: jafrmartins
Author-email: j.afr.martins@outlook.pt
Keywords: sqlite encrypted inmemory orm
